Metadata-Version: 2.4
Name: wipac-dev-next-version-action-testbed
Version: 1.1.17
Summary: A guinea pig for testing the `wipac-dev-next-version-action`
Author-email: WIPAC Developers <developers@icecube.wisc.edu>
License: MIT License
Keywords: WIPAC,CI/CD,gitops,testbed
Classifier: Programming Language :: Python :: 3.13
Requires-Python: <3.14,>=3.12
License-File: LICENSE
Requires-Dist: numpy
Requires-Dist: oms-mqclient
Dynamic: license-file
